CHANGELOG.md
plaster_yaml-3.0.0.dist-info/METADATA
plaster_yaml-3.0.0.dist-info/WHEEL
plaster_yaml-3.0.0.dist-info/entry_points.txt
plaster_yaml-3.0.0.dist-info/licenses/LICENSE
plaster_yaml/__init__.py
plaster_yaml/compat.py
plaster_yaml/loader.py
plaster_yaml/py.typed
plaster_yaml-3.0.0.dist-info/RECORD
