Metadata-Version: 2.1
Name: plaster-yaml
Version: 3.0.0
Summary: A plaster plugin to configure pyramid app with Yaml
Author-Email: Guillaume Gauvrit <guillaume@gauvr.it>
License: BSD-derived
Project-URL: Homepage, https://github.com/mardiros/plaster-yaml
Project-URL: Documentation, https://github.com/mardiros/plaster-yaml/blob/main/README.md
Project-URL: Repository, https://github.com/mardiros/plaster-yaml.git
Project-URL: Issues, https://github.com/mardiros/plaster-yaml/issues
Project-URL: Changelog, https://github.com/mardiros/plaster-yaml/blob/main/CHANGELOG.md
Requires-Python: >=3.9
Requires-Dist: importlib-metadata>=7.1.0; python_version <= "3.10"
Requires-Dist: plaster<2,>=1.0
Requires-Dist: PyYAML<7,>=6.0.1
Requires-Dist: envsub<0.2,>=0.1.15
